dbrick/__init__.py
databricks_uc_apis-0.0.7.dist-info/METADATA
databricks_uc_apis-0.0.7.dist-info/WHEEL
databricks_uc_apis-0.0.7.dist-info/top_level.txt
databricks_uc_apis-0.0.7.dist-info/RECORD
